flask_rest_controller
tests
