Metadata-Version: 1.1
Name: Flask-REST-Controller
Version: 1.0.0
Summary: Flask-REST-Controller is added Class-Based-View(Controller) extension on Flask
Home-page: https://github.com/teitei-tk/Flask-REST-Controller
Author: teitei-tk
Author-email: teitei.tk@gmail.com
License: MIT
Download-URL: https://github.com/teitei-tk/Flask-REST-Controller/archive/master.tar.gz
Keywords: flask,controller,view,cbv
Platform: UNKNOWN
Classifier: Development Status :: 5 - Production/Stable
Classifier: Environment :: Web Environment
Classifier: Framework :: Flask
Classifier: License :: OSI Approved :: MIT License
Classifier: Programming Language :: Python
Classifier: Programming Language :: Python :: 2.6
Classifier: Programming Language :: Python :: 2.7
Classifier: Programming Language :: Python :: 3
Classifier: Topic :: Software Development
Classifier: Topic :: Internet :: WWW/HTTP :: Dynamic Content
Classifier: Topic :: Software Development :: Libraries
